modde/__init__.py
modde/asktellde.py
modde/modularde.py
modde/parameters.py
modde/population.py
modde/sampling.py
modde/utils.py
tests/__init__.py
tests/create_expected.py
tests/test_asktell.py
tests/test_modularde.py
modde-0.0.4.dist-info/LICENCE
modde-0.0.4.dist-info/METADATA
modde-0.0.4.dist-info/WHEEL
modde-0.0.4.dist-info/top_level.txt
modde-0.0.4.dist-info/RECORD
