Metadata-Version: 2.1
Name: modde
Version: 0.0.4
Summary: Package Containing Modular DE optimizer
Author: Diederick Vermetten
Author-email: d.l.vermetten@liacs.leidenuniv.nl
Classifier: Programming Language :: Python :: 3
Classifier: License :: OSI Approved :: MIT License
Classifier: Operating System :: OS Independent
License-File: LICENCE
Requires-Dist: numpy
Requires-Dist: scipy
Requires-Dist: ioh
